{"name":"ingresar al sistema por primera vez","id":"yo-como-usuario-del-servicio;ingresar-al-sistema-por-primera-vez","testSteps":[{"number":1,"description":"Given que Elvis esta en el portal","duration":16111,"startTime":"2020-07-10T18:55:58.299-05:00[America/Bogota]","screenshots":[{"screenshot":"c14b3e2591130e026c2b2a99f4406ddd94576e79202e2502bd2dd8730dbe7d0d.png","timeStamp":1594425374410}],"result":"SUCCESS","precondition":false,"level":0,"children":[{"number":2,"description":"Elvis abrir navegador","duration":15697,"startTime":"2020-07-10T18:55:58.709-05:00[America/Bogota]","screenshots":[{"screenshot":"c14b3e2591130e026c2b2a99f4406ddd94576e79202e2502bd2dd8730dbe7d0d.png","timeStamp":1594425374406}],"result":"SUCCESS","precondition":false,"level":1,"children":[{"number":3,"description":"Elvis opens the https://www.demoblaze.com","duration":15650,"startTime":"2020-07-10T18:55:58.744-05:00[America/Bogota]","screenshots":[{"screenshot":"c14b3e2591130e026c2b2a99f4406ddd94576e79202e2502bd2dd8730dbe7d0d.png","timeStamp":1594425374393}],"result":"SUCCESS","precondition":false,"level":2}]}]},{"number":4,"description":"When el seleciona el producto a comprar","duration":6,"startTime":"2020-07-10T18:56:14.410-05:00[America/Bogota]","screenshots":[{"screenshot":"c14b3e2591130e026c2b2a99f4406ddd94576e79202e2502bd2dd8730dbe7d0d.png","timeStamp":1594425374415}],"result":"SUCCESS","precondition":false,"level":0},{"number":5,"description":"Then el usuario debe ver el nombre Product added","duration":4,"startTime":"2020-07-10T18:56:14.416-05:00[America/Bogota]","screenshots":[{"screenshot":"c14b3e2591130e026c2b2a99f4406ddd94576e79202e2502bd2dd8730dbe7d0d.png","timeStamp":1594425374419}],"result":"SUCCESS","precondition":false,"level":0}],"userStory":{"id":"yo-como-usuario-del-servicio","storyName":"yo como usuario del servicio","path":"src/test/resources/feature/comprar.feature","narrative":"  Necesito registrar la cuenta en  linkedin\n  Para estar registrado en el sistema","type":"feature"},"featureTag":{"name":"Feature/yo como usuario del servicio","type":"feature"},"title":"ingresar al sistema por primera vez","startTime":"2020-07-10T18:55:57.990-05:00[America/Bogota]","duration":16430,"projectKey":"","sessionId":"af55a14532a8e6f74e7cb3007d0340c4","driver":"chrome","manual":false,"testSource":"Cucumber","actors":[{"name":"Elvis","can":["browse the web"]}],"result":"SUCCESS"}